matic/__init__.py
matic/abstracts.py
matic/constants.py
matic/exceptions.py
matic/json_types.py
matic/services.py
matic/plasma/__init__.py
matic/plasma/contracts.py
matic/plasma/erc_20.py
matic/plasma/erc_721.py
matic/plasma/plasma_token.py
matic/pos/__init__.py
matic/pos/erc_1155.py
matic/pos/erc_20.py
matic/pos/erc_721.py
matic/pos/pos_token.py
matic/pos/root_chain_manager.py
matic/utils/__init__.py
matic/utils/abi_manager.py
matic/utils/base_token.py
matic/utils/bridge_client.py
matic/utils/exit_util.py
matic/utils/merkle_tree.py
matic/utils/polyfill.py
matic/utils/proof_utils.py
matic/utils/root_chain.py
matic/utils/web3_side_chain_client.py
matic/web3_client/__init__.py
matic/web3_client/utils.py
matic-0.1.0b2.dist-info/LICENSE.md
matic-0.1.0b2.dist-info/METADATA
matic-0.1.0b2.dist-info/WHEEL
matic-0.1.0b2.dist-info/top_level.txt
matic-0.1.0b2.dist-info/RECORD
