Metadata-Version: 2.1
Name: matic
Version: 0.1.0b2
Summary: Python port of matic.js - library to interact with Polygon blockchain
Author-email: sterliakov <terlya.stas@gmail.com>
License: GNU GENERAL PUBLIC LICENSE
Project-URL: Home, https://github.com/sterliakov/pymatic
Project-URL: Source, https://github.com/sterliakov/pymatic
Project-URL: Issues, https://github.com/sterliakov/pymatic/issues
Project-URL: Documentation, https://readthedocs.org/projects/pymatic/badge/?version=latest
Keywords: blockchain,sdk,ethereum
Classifier: Programming Language :: Python :: 3.8
Classifier: Programming Language :: Python :: 3.9
Classifier: Programming Language :: Python :: 3.10
Classifier: Intended Audience :: Developers
Classifier: Topic :: Software Development :: Build Tools
Classifier: License :: OSI Approved :: GNU General Public License v3 (GPLv3)
Classifier: Operating System :: OS Independent
Classifier: Development Status :: 4 - Beta
Classifier: Typing :: Typed
Requires-Python: >=3.8
License-File: LICENSE.md
Requires-Dist: eth-utils (~=1.10.0)
Requires-Dist: eth-abi (~=2.1.1)
Requires-Dist: eth-typing (~=2.3)
Requires-Dist: hexbytes (~=0.3.0)
Requires-Dist: pysha3 (~=1.0.2)
Requires-Dist: requests (~=2.28)
Requires-Dist: rlp (~=2.0.1)
Requires-Dist: web3 (~=5.30.0)
Requires-Dist: ethers (~=0.1.1)
Requires-Dist: merkle-patricia-trie (~=0.3.1)
Requires-Dist: typing-extensions (~=4.3.0)
Requires-Dist: python-dotenv
Provides-Extra: docs
Requires-Dist: docutils (<0.18,>=0.14) ; extra == 'docs'
Requires-Dist: sphinx (<5.0.0,>=4.5.0) ; extra == 'docs'
Requires-Dist: sphinx-rtd-theme ; extra == 'docs'
Requires-Dist: autodocsumm (<0.3.0,>=0.2.8) ; extra == 'docs'
Provides-Extra: test
Requires-Dist: pytest (>=6.4.0) ; extra == 'test'
Requires-Dist: pytest-cov ; extra == 'test'
Requires-Dist: pytest-mock ; extra == 'test'
Requires-Dist: pytest-subtests ; extra == 'test'
Requires-Dist: pre-commit ; extra == 'test'
